casablanca_Stock/Action.py
casablanca_Stock/Top_Low.py
casablanca_Stock/__init__.py
casablanca_Stock/copilot.py
casablanca_Stock/financial_copilot.py
casablanca_Stock/index.py
casablanca_Stock/instruments.py
casablanca_Stock-1.2.9.dist-info/LICENSE
casablanca_Stock-1.2.9.dist-info/METADATA
casablanca_Stock-1.2.9.dist-info/WHEEL
casablanca_Stock-1.2.9.dist-info/top_level.txt
casablanca_Stock-1.2.9.dist-info/RECORD
