Metadata-Version: 2.1
Name: casablanca-Stock
Version: 1.2.9
License-File: LICENSE
Requires-Dist: requests
Requires-Dist: beautifulsoup4
Requires-Dist: pandas
Requires-Dist: selenium
Requires-Dist: streamlit
Requires-Dist: groq
